CHANGES.rst
LICENSE
MANIFEST.in
README.rst
setup.py
django_external_feed.egg-info/PKG-INFO
django_external_feed.egg-info/SOURCES.txt
django_external_feed.egg-info/dependency_links.txt
django_external_feed.egg-info/not-zip-safe
django_external_feed.egg-info/requires.txt
django_external_feed.egg-info/top_level.txt
externalfeed/__init__.py
externalfeed/urls.py
externalfeed/utils.py
externalfeed/views.py
externalfeed/locale/nl/LC_MESSAGES/django.mo
externalfeed/locale/nl/LC_MESSAGES/django.po
externalfeed/templates/externalfeed/entry.html
externalfeed/templates/externalfeed/entry_snippet.html
externalfeed/templates/externalfeed/feeds_snippet.html
externalfeed/templates/externalfeed/index.html
externalfeed/templates/externalfeed/list.html
externalfeed/templates/externalfeed/single_feed_snippet.html
externalfeed/templatetags/__init__.py
externalfeed/templatetags/feeder.py