Metadata-Version: 1.1
Name: django-external-feed
Version: 0.1
Summary: Show content from an XML feed on your own site.
Home-page: https://github.com/nederhoed/django-external-feed
Author: Maurits van Rees
Author-email: m.van.rees@zestsoftware.nl
License: GPL
Keywords: rss atom syndication
Platform: UNKNOWN
Classifier: Development Status :: 3 - Alpha
Classifier: Environment :: Web Environment
Classifier: Framework :: Django
Classifier: License :: OSI Approved :: GNU General Public License v3 (GPLv3)
Classifier: Operating System :: OS Independent
Classifier: Programming Language :: Python
